pydocx/__init__.py
pydocx/__main__.py
pydocx/constants.py
pydocx/exceptions.py
pydocx/models.py
pydocx/packaging.py
pydocx/pydocx.py
pydocx/types.py
pydocx/export/__init__.py
pydocx/export/base.py
pydocx/export/html.py
pydocx/export/markdown.py
pydocx/export/numbering_span.py
pydocx/export/mixins/__init__.py
pydocx/export/mixins/faked_superscript_and_subscript.py
pydocx/openxml/__init__.py
pydocx/openxml/drawing/__init__.py
pydocx/openxml/drawing/blip.py
pydocx/openxml/drawing/extents.py
pydocx/openxml/drawing/graphic.py
pydocx/openxml/drawing/graphic_data.py
pydocx/openxml/drawing/transform_2d.py
pydocx/openxml/drawing/pictures/__init__.py
pydocx/openxml/drawing/pictures/blip_fill.py
pydocx/openxml/drawing/pictures/picture.py
pydocx/openxml/drawing/pictures/shape_properties.py
pydocx/openxml/drawing/wordprocessing/__init__.py
pydocx/openxml/drawing/wordprocessing/anchor.py
pydocx/openxml/drawing/wordprocessing/inline.py
pydocx/openxml/markup_compatibility/__init__.py
pydocx/openxml/markup_compatibility/alternate_content.py
pydocx/openxml/markup_compatibility/fallback.py
pydocx/openxml/packaging/__init__.py
pydocx/openxml/packaging/font_table_part.py
pydocx/openxml/packaging/footnotes_part.py
pydocx/openxml/packaging/image_part.py
pydocx/openxml/packaging/main_document_part.py
pydocx/openxml/packaging/numbering_definitions_part.py
pydocx/openxml/packaging/open_xml_package.py
pydocx/openxml/packaging/open_xml_part.py
pydocx/openxml/packaging/open_xml_part_container.py
pydocx/openxml/packaging/style_definitions_part.py
pydocx/openxml/packaging/word_processing_document.py
pydocx/openxml/vml/__init__.py
pydocx/openxml/vml/image_data.py
pydocx/openxml/vml/rect.py
pydocx/openxml/vml/shape.py
pydocx/openxml/vml/textbox.py
pydocx/openxml/wordprocessing/__init__.py
pydocx/openxml/wordprocessing/abstract_num.py
pydocx/openxml/wordprocessing/body.py
pydocx/openxml/wordprocessing/bookmark.py
pydocx/openxml/wordprocessing/br.py
pydocx/openxml/wordprocessing/deleted_run.py
pydocx_fork-0.9.11.dist-info/licenses/AUTHORS
pydocx_fork-0.9.11.dist-info/licenses/LICENSE
pydocx_fork-0.9.11.dist-info/METADATA
pydocx_fork-0.9.11.dist-info/WHEEL
pydocx_fork-0.9.11.dist-info/entry_points.txt
pydocx_fork-0.9.11.dist-info/top_level.txt
pydocx_fork-0.9.11.dist-info/RECORD
